issim/__init__.py
issim/issim.py
issim/galgen/__init__.py
issim/galgen/galgen.py
issim-0.1.0.dist-info/LICENSE
issim-0.1.0.dist-info/METADATA
issim-0.1.0.dist-info/WHEEL
issim-0.1.0.dist-info/top_level.txt
issim-0.1.0.dist-info/RECORD
