Metadata-Version: 2.1
Name: issim
Version: 0.1.0
Summary: A Python package for simulating ISM in galaxies
Home-page: https://github.com/dannytalk/ISsiM
Author: Sean Lewis
Author-email: sean.lewis@yale.edu
License: MIT
Classifier: License :: OSI Approved :: MIT License
Classifier: Development Status :: 1 - Planning
Classifier: Intended Audience :: Science/Research
Classifier: Programming Language :: Python :: 3
Classifier: Operating System :: Unix
Classifier: Operating System :: MacOS :: MacOS X
Classifier: Operating System :: Microsoft :: Windows
Requires-Python: >=3
License-File: LICENSE
Requires-Dist: numpy
Requires-Dist: scipy
Requires-Dist: matplotlib
Requires-Dist: astropy
Requires-Dist: IPython
Requires-Dist: tqdm
Requires-Dist: ffmpeg
